{
	"credit": "Made by CiscuLog with Blockbench",
	"texture_size": [64, 48],
	"textures": {
		"0": "siscu_se:item/villager_skulls/villager_skull",
		"particle": "siscu_se:item/villager_skulls/villager_skull"
	},
	"elements": [
		{
			"from": [4, 4.25, 4],
			"to": [12, 14.25, 12],
			"faces": {
				"north": {"uv": [2, 2.66667, 4, 6], "texture": "#0"},
				"east": {"uv": [0, 2.66667, 2, 6], "texture": "#0"},
				"south": {"uv": [6, 2.66667, 8, 6], "texture": "#0"},
				"west": {"uv": [4, 2.66667, 6, 6], "texture": "#0"},
				"up": {"uv": [4, 2.66667, 2, 0], "texture": "#0"},
				"down": {"uv": [6, 0, 4, 2.66667], "texture": "#0"}
			}
		},
		{
			"from": [4.1, 4.35, 11.85],
			"to": [11.9, 14.15, 4.05],
			"faces": {
				"north": {"uv": [8, 2.66667, 6, 6], "texture": "#0"},
				"east": {"uv": [2, 2.66667, 0, 6], "texture": "#0"},
				"south": {"uv": [4, 2.66667, 2, 6], "texture": "#0"},
				"west": {"uv": [6, 2.66667, 4, 6], "texture": "#0"},
				"up": {"uv": [4, 0, 2, 2.66667], "texture": "#0"},
				"down": {"uv": [6, 2.66667, 4, 0], "texture": "#0"}
			}
		},
		{
			"from": [3.5, 3.75, 3.5],
			"to": [12.5, 14.75, 12.5],
			"faces": {
				"north": {"uv": [10, 2.66667, 12, 6], "texture": "#0"},
				"east": {"uv": [8, 2.66667, 10, 6], "texture": "#0"},
				"south": {"uv": [14, 2.66667, 16, 6], "texture": "#0"},
				"west": {"uv": [12, 2.66667, 14, 6], "texture": "#0"},
				"up": {"uv": [12, 2.66667, 10, 0], "texture": "#0"},
				"down": {"uv": [14, 0, 12, 2.66667], "texture": "#0"}
			}
		},
		{
			"from": [4.1, 4.35, 11.85],
			"to": [11.9, 14.15, 4.05],
			"faces": {
				"north": {"uv": [16, 2.66667, 14, 6], "texture": "#0"},
				"east": {"uv": [10, 2.66667, 8, 6], "texture": "#0"},
				"south": {"uv": [12, 2.66667, 10, 6], "texture": "#0"},
				"west": {"uv": [14, 2.66667, 12, 6], "texture": "#0"},
				"up": {"uv": [12, 0, 10, 2.66667], "texture": "#0"},
				"down": {"uv": [14, 2.66667, 12, 0], "texture": "#0"}
			}
		},
		{
			"from": [12.5, 3.75, 3.5],
			"to": [3.5, 14.75, 12.5],
			"faces": {
				"north": {"uv": [12, 2.66667, 10, 6], "texture": "#0"},
				"east": {"uv": [14, 2.66667, 12, 6], "texture": "#0"},
				"south": {"uv": [16, 2.66667, 14, 6], "texture": "#0"},
				"west": {"uv": [10, 2.66667, 8, 6], "texture": "#0"},
				"up": {"uv": [10, 2.66667, 12, 0], "texture": "#0"},
				"down": {"uv": [14, 0, 12, 2.66667], "texture": "#0"}
			}
		},
		{
			"from": [4.1, 4.35, 11.85],
			"to": [11.9, 14.15, 4.05],
			"faces": {
				"north": {"uv": [16, 2.66667, 14, 6], "texture": "#0"},
				"east": {"uv": [10, 2.66667, 8, 6], "texture": "#0"},
				"south": {"uv": [12, 2.66667, 10, 6], "texture": "#0"},
				"west": {"uv": [14, 2.66667, 12, 6], "texture": "#0"},
				"up": {"uv": [12, 0, 10, 2.66667], "texture": "#0"},
				"down": {"uv": [14, 2.66667, 12, 0], "texture": "#0"}
			}
		}
	],
	"display": {
		"head": {
			"translation": [0, 2.5, 0],
			"scale": [2.4, 2.4, 2.4]
		}
	}
}